{"questions":[{"answer":["どのように"],"question":"心細げなるありさま、<bold>いかで</bold>すぐすらんと、いと心苦し。"},{"answer":["どうして"],"question":"「<bold>いかで</bold>月を見ではあらむ」とで、なほ月出づれば、出でゐつつ嘆き思へり。"},{"answer":["何とかして"],"question":"今は、<bold>いかで</bold>この若き人々大人びさせむと思ふよりほかのことなきに、"},{"answer":["なんとかして"],"question":"<bold>いかで</bold>このかぐや姫を得てしがな、"},{"answer":["どのように"],"question":"あはれ、<bold>いかに</bold>し給はむずらむ"},{"answer":["どのように"],"question":"昔、男ありけり。<bold>いかが</bold>ありけむ、その男住まわずなりにけり。"},{"answer":["どうして"],"question":"かくばかり逢ふ日のまれになる人を<bold>いかが</bold>つらしと思はざるべき。"},{"answer":["どんなにか"],"question":"このごろの山の紅葉は<bold>いかに</bold>をかしからむ。"},{"answer":["どうして"],"question":"「<bold>など</bold>答へもせぬ」と言へば、"},{"answer":["どうして"],"question":"<bold>なぞ</bold>かう暑きにこの格子はおろされたる"},{"answer":["いつの間にか"],"question":"うぐいすばかりぞ<bold>いつしか</bold>音したるを、あはれと聞く"},{"answer":["早く"],"question":"<bold>いつしか</bold>梅咲かなむ"},{"answer":["たまたま"],"question":"<bold>おのづから</bold>人の上などうち言ひそしりたるに、幼き子供の聞き取りて、"},{"answer":["もしかして"],"question":"<bold>おのづから</bold>歌などや、入ると思ひて。"},{"answer":["依然として"],"question":"風波やまねば、<bold>なほ</bold>おなじところにあり。"},{"answer":["さらに"],"question":"東路の道の果てよりも、<bold>なほ</bold>奥つ方に生ひ出でたる人"},{"answer":["ますます"],"question":"散ればこそ<bold>いとど</bold>桜はめでたけれ"},{"answer":["一層甚だしい"],"question":"<bold>いとどしき</bold>朝霧にいづこともなく惑ふ心地し給ふ"},{"answer":["ますます"],"question":"ありしより<bold>けに</bold>恋しくのみおぼえければ"},{"answer":["本当に"],"question":"<bold>げに</bold>あくがるると思ひて"},{"answer":["このような"],"question":"<bold>かかる</bold>目見むとは思はざりけむ"},{"answer":["そのように"],"question":"必ず<bold>さ</bold>おぼす故はべらむかし"},{"answer":["そうしたら"],"question":"和歌一つづつ仕うまつれ。<bold>さらば</bold>許さむ。"},{"answer":["すぐに"],"question":"名を聞くより<bold>やがて</bold>面影は推しはかるる心地するを"},{"answer":["しだいに"],"question":"春はあけぼの。<bold>やうやう</bold>白くなりゆく山際"},{"answer":["そっと"],"question":"奥の方より<bold>やをら</bold>覗いたるも、いとをかし"},{"answer":["中途半端に"],"question":"<bold>なかなか</bold>返事をして、門立てられ、錠されては"},{"answer":["かえって"],"question":"<bold>なかなか</bold>に寝も寝られず。"},{"answer":["なんといってもやはり"],"question":"男君も、<bold>さすがに</bold>貴人の子となれば、"},{"answer":["互いに"],"question":"<bold>かたみ</bold>に思ふ"},{"answer":["嫌な感じに"],"question":"花も散りたるのちは、<bold>うたて</bold>ぞ見ゆる。"},{"answer":["一般に"],"question":"<bold>なべて</bold>心やはらかに、情けあるゆゑに、"},{"answer":["特に"],"question":"<bold>わざと</bold>めでたき冊子ども、硯の箱の蓋に入れたり"},{"answer":["正式な"],"question":"<bold>わざとの</bold>御学問はさるものにて、"},{"answer":["ことさらでない"],"question":"<bold>わざとならぬ</bold>匂ひしめやかにうち薫りて、"},{"answer":["たくさん"],"question":"女御・更衣<bold>あまた</bold>さぶらひ給ひけるなかに、"},{"answer":["たくさん"],"question":"<bold>そこばく</bold>の捧げものを木の枝につけて、"},{"answer":["たくさん"],"question":"<bold>そこら</bold>の人のほめ感心して、"},{"answer":["たいそう"],"question":"<bold>ここら</bold>悲しきさまざまの愁はしさはさし置かれて、"},{"answer":["～できない"],"question":"この玉たはやすく<bold>え</bold>取ら<bold>じ</bold>を、"},{"answer":["何とも言えないほど"],"question":"頭も<bold>えもいわず</bold>恐ろしげなる者どもなり"},{"answer":["そのようにしてはならない"],"question":"さなせそ"},{"answer":["だいたい"],"question":"<bold>おほかた</bold>、振る舞ひて興あるよりも、"},{"answer":["まったく"],"question":"<bold>さらに</bold>まだ見ぬ骨のさまなり"},{"answer":["まったく"],"question":"空をあふぎて、<bold>よに</bold>得ぬけしきにて帰りてけり"},{"answer":["実に"],"question":"梨の花、<bold>よに</bold>すさまじきものにして、"},{"answer":["けっして"],"question":"<bold>ゆめゆめ</bold>粗略を存ずまじう候ふ"},{"answer":["けっして"],"question":"<bold>ゆめ</bold>この雪落とすな"},{"answer":["まったく"],"question":"木の葉をかきのけたれど、<bold>つやつや</bold>ものも見えず"},{"answer":["ほとんど"],"question":"冬の景色こそ、秋には<bold>をさをさ</bold>おとるまじけれ"},{"answer":["まさか"],"question":"今は<bold>よも</bold>烏に取られじ。"},{"answer":["決して決して"],"question":"<bold>あなかしこあなかしこ</bold>、人に語りたまふな"},{"answer":["気持ちを静める"],"question":"大将も、とみにえ<bold>ためらひ</bold>たまはず。"},{"answer":["ためらう"],"question":"たやすくうち出でんもいかがと<bold>ためらひ</bold>けるを、"},{"answer":["立ち止まる"],"question":"いといみじき花の陰に、しばしも<bold>やるらは</bold>ず、"},{"answer":["親しく語り合う"],"question":"<bold>かたらは</bold>ばなぐさむこともありやせむ"},{"answer":["くつろぐ"],"question":"唐衣も汗衫も着ず、みな<bold>うちとけ</bold>たれば、"},{"answer":["親しく交際する"],"question":"<bold>かたらふ</bold>どちは見せかはしなどするも、"},{"answer":["契って"],"question":"さるべきところに、宮仕へける女房を<bold>かたらひ</bold>て、"},{"answer":["説得する"],"question":"子君を<bold>かたらひ</bold>給へど、"},{"answer":["通う"],"question":"男、<bold>すま</bold>ずになりにけり"},{"answer":["終わらせる"],"question":"なほこのこと、勝ち負けなくて<bold>やま</bold>せ給はん。"},{"answer":["終わる"],"question":"翁、この子を見れば、苦しきことも<bold>やみ</bold>ぬ。"},{"answer":["色あせる"],"question":"<bold>移ろひ</bold>たる菊。"},{"answer":["外を見る"],"question":"戸口の局に<bold>見出せ</bold>ば、"},{"answer":["浮かれ歩く"],"question":"いさよふ月に、ゆくりなく<bold>あくがれ</bold>むことを、女は思ひ"},{"answer":["扱う"],"question":"いづれをもなだらかに<bold>もてなし</bold>て、"},{"answer":["ふるまう"],"question":"涙も出づれど、つれなく<bold>もてなし</bold>て、"},{"answer":["空を暗くする"],"question":"雪の<bold>かきくらし</bold>降るに、"},{"answer":["悲しみに暮れる"],"question":"また、<bold>かきくらさ</bold>るるさまぞ、いふかたなき"},{"answer":["涙を流す"],"question":"いと悲しうて、人知れず<bold>しほたれ</bold>けり"},{"answer":["耐えられない"],"question":"霜に<bold>あへず</bold>枯れにし園の菊なれど、"},{"answer":["結婚する"],"question":"この世の人は、男は女に<bold>あふ</bold>ことをする。"},{"answer":["～しきれない"],"question":"念じ<bold>あへず</bold>うち泣くけはひあはれなり"},{"answer":["差支えないだろう"],"question":"小さきは<bold>あへなむ</bold>"},{"answer":["結婚させる"],"question":"父はこと人に<bold>あはせ</bold>むといひけるを、"},{"answer":["迷う"],"question":"道知れる人もなくて、<bold>惑ひ</bold>行きけり"},{"answer":["ひどく～する"],"question":"頬なども腫れ<bold>まどひ</bold>て、"},{"answer":["だまそう"],"question":"仲のあしかりければ、「<bold>たばから</bold>ん」と思ひて"},{"answer":["興じる"],"question":"笛をえならず吹き<bold>すさび</bold>たる、"},{"answer":["抵抗する"],"question":"女もいやしければ、<bold>すまふ</bold>力なし。"},{"answer":["まねる"],"question":"人の言ふらむことを<bold>まねぶ</bold>らむよ。"},{"answer":["伝え"],"question":"かの御車の所争ひを<bold>まねび</bold>きこゆる人ありければ"},{"answer":["訴える"],"question":"御門に<bold>うれへ</bold>申せば、"},{"answer":["決めておく"],"question":"よろづに見ざらん世までを思ひ<bold>おきて</bold>んこそ"},{"answer":["発生する"],"question":"うたかたは、かつ消え、かつ<bold>むすびて</bold>"},{"answer":["訪ねる"],"question":"三年幽居のあとを<bold>とぶらひ</bold>"},{"answer":["目立たない様子で"],"question":"いといたく<bold>やつれ</bold>給へれど"},{"answer":["嘆く"],"question":"かこつ"},{"answer":["理解する"],"question":"そのおそくとき花の心をよく<bold>わき</bold>て"},{"answer":["差し支える"],"question":"八日、<bold>さはる</bold>こと"},{"answer":["遠慮する"],"question":"つつむ"},{"answer":["理想的だ"],"question":"あらまほし"},{"answer":["巧みに"],"question":"いとをかしげに<bold>らうらうじ</bold>くかきたり"},{"answer":["上品で"],"question":"らうらうじう愛敬"},{"answer":["しっかりしている"],"question":"はかばかし"},{"answer":["しっかりしている"],"question":"をさをさし"},{"answer":["２つとなくすばらしい"],"question":"さうなし"},{"answer":["すべがない"],"question":"ずちなし"},{"answer":["つまらない"],"question":"世に語りつたふること、まことに<bold>あいなき</bold>に"},{"answer":["なんとなく"],"question":"<bold>あいなう</bold>心苦し"},{"answer":["よくない"],"question":"まさなし"},{"answer":["たよりない"],"question":"などてかく<bold>はかなき</bold>宿"},{"answer":["ちょっとした"],"question":"<bold>はかなき</bold>文つけなどだにせず"},{"answer":["気に食わない"],"question":"こころづきなし"},{"answer":["落胆している"],"question":"御使いもいと<bold>あへなく</bold>て"},{"answer":["はかなく"],"question":"<bold>あへなく</bold>うせ給ひぬ"},{"answer":["身の程知らず"],"question":"おほけなし"},{"answer":["つまらない"],"question":"ようなきありしは<bold>よしなかり</bold>けり"},{"answer":["関係がない"],"question":"あらぬよしなきもの"}],"name":"古典単語Part1","description":"古典単語リストPart1","author":"yuki-js"}